Workbook

Sheet ENUNCIADO
B2: Empresa : NETWORK SOLUTIONS PANAMÁ, S.A
B3: Transacciones del mes de Febrero
A4: Fecha: | B4: Enunciado:
A5: 36923 | B5: Aporte de capital por B/.185,000.00 depositado en Scotiabank.NAMÁ, S.A
A6: 37653 | B6: Se establece caja menuda por B/.300.00 mediante cheque No. 2201.
A7: 38384 | B7: Compra de herramientas técnicas para instalación de redes por B/.5,600.00 más ITBMS mediante cheque No. 2202
A8: 39845 | B8: Compra de mobiliario de oficina por B/.3,400.00 más ITBMS a crédito.
A9: 41306 | B9: Se presta un servicio de implementación de red corporativa por B/.11,800.00 más ITBMS. El cliente paga el 30% por transferencia y el resto queda a crédito.
A10: 42036 | B10: Pago de salarios por B/.5,900.00 mediante cheque No. 2203.
A11: 43497 | B11: Pago de gastos de mercadeo por B/.749.00 (incluye ITBMS) mediante cheque No. 2204.
A12: 44958 | B12: Se recibe transferencia bancaria por el saldo pendiente de la venta del 13 de febrero.
A13: 46054 | B13: Se realiza un abono de B/.1,500.00 a la cuenta por pagar de mobiliario mediante cheque No. 2205.
A14: 46784 | B14: Pago de servicios públicos por B/.580.00 (incluye ITBMS) mediante cheque No. 2206.

Sheet BALANCE
A2: NETWORK SOLUTIONS PANAMÁ, S.A.
A3: BALANCE DE PRUEBA O COMPROBACIÓN
A4: Del 1 al 31 de Febrero
A5: (en Balboas)
A7: NOMBRE DE LA CUENTA | B7: DR | D7: CR
A8: =DIARIO!U3 -> Caja Menuda | B8: 300
A9: =DIARIO!U4 -> Banco | B9: 182605
A10: =DIARIO!U5 -> Cuentas por Cobrar | B10: 0 | D10: 0
A11: =DIARIO!U6 -> Mobiliario de Oficina | B11: 3400
A12: =DIARIO!U7 -> Equipo de Oficina | B12: 5600
A13: =DIARIO!U8 -> Cuentas por pagar | D13: 1138
A14: =DIARIO!U9 -> Tesoro Nacional - ITBMS | D14: 826
A15: =DIARIO!U10 -> Capital | D15: 185000
A16: =DIARIO!U11 -> Ingresos - Servicio Profesional | D16: 11800
A17: =DIARIO!U12 -> Gasto - Salarios | B17: 5900
A18: =DIARIO!U13 -> Gasto - Publicidad | B18: 696.57
A19: =DIARIO!U14 -> Gastos - servicios públicos | B19: 539.4
A20: =DIARIO!U15 -> Gasto - ITBMS | B20: 723.03
A21: Totales | B21: =SUM(B8:B20) -> 199764 | D21: =SUM(D8:D20) -> 198764
A24: ESTADO FINANCIERO : Según el balance la empresa presenta ingresos bajos pero es debido a su recien inicio. Como punto interesante es que aunque es nueva ya tiene un gasto alto para el salario. A su vez aun presentan deudas que pagar en cual se remonta a la compra de un mobiliario de oficina.Como punto positivo o fuerte tiene un monto disponible para futuros gastos y operaciones.

Sheet MAYOR
A1: HOJA DE MAYOR
A3: =DIARIO!U3 -> Caja Menuda | I3: No. | K3: =DIARIO!V3 -> 101
A4: FECHA | C4: DETALLE | D4: REF. | E4: DÉBITO | G4: FECHA | I4: DETALLE | J4: REF. | K4: CRÉDITO
A5: Febrero | B5: 3 | D5: 80 | E5: 300 | J5: =IF(H5<>"",RIGHT(DIARIO!F1,LEN(DIARIO!F1)-1),"")
D6: =IF(B6<>"",RIGHT(DIARIO!F2,LEN(DIARIO!F2)-1),"") | J6: =IF(H6<>"",RIGHT(DIARIO!F2,LEN(DIARIO!F2)-1),"")
D7: =IF(B7<>"",RIGHT(DIARIO!F3,LEN(DIARIO!F3)-1),"") | J7: =IF(H7<>"",RIGHT(DIARIO!F3,LEN(DIARIO!F3)-1),"")
D8: =IF(B8<>"",RIGHT(DIARIO!F4,LEN(DIARIO!F4)-1),"") | J8: =IF(H8<>"",RIGHT(DIARIO!F4,LEN(DIARIO!F4)-1),"")
D9: =IF(B9<>"",RIGHT(DIARIO!F5,LEN(DIARIO!F5)-1),"") | J9: =IF(H9<>"",RIGHT(DIARIO!F5,LEN(DIARIO!F5)-1),"")
D10: =IF(B10<>"",RIGHT(DIARIO!F6,LEN(DIARIO!F6)-1),"") | J10: =IF(H10<>"",RIGHT(DIARIO!F6,LEN(DIARIO!F6)-1),"")
D11: =IF(B11<>"",RIGHT(DIARIO!F7,LEN(DIARIO!F7)-1),"") | J11: =IF(H11<>"",RIGHT(DIARIO!F7,LEN(DIARIO!F7)-1),"")
D12: =IF(B12<>"",RIGHT(DIARIO!F8,LEN(DIARIO!F8)-1),"") | J12: =IF(H12<>"",RIGHT(DIARIO!F8,LEN(DIARIO!F8)-1),"")
A14: =DIARIO!U4 -> Banco | I14: No. | K14: =DIARIO!V4 -> 110
A15: FECHA | C15: DETALLE | D15: REF. | E15: DÉBITO | G15: FECHA | I15: DETALLE | J15: REF. | K15: CRÉDITO
A16: Febrero | B16: 1 | D16: =IF(B16<>"",RIGHT(DIARIO!$F$1,LEN(DIARIO!$F$1)-1),"") -> 80 | E16: 185000 | G16: Febrero | H16: 3 | J16: =IF(H16<>"",RIGHT(DIARIO!$F$1,LEN(DIARIO!$F$1)-1),"") -> 80 | K16: 300
B17: 13 | D17: =IF(B17<>"",RIGHT(DIARIO!$F$1,LEN(DIARIO!$F$1)-1),"") -> 80 | E17: 3787.8 | H17: 5 | J17: =IF(H17<>"",RIGHT(DIARIO!$F$1,LEN(DIARIO!$F$1)-1),"") -> 80 | K17: 5992 | L17: 5992
B18: 23 | D18: =IF(B18<>"",RIGHT(DIARIO!$F$1,LEN(DIARIO!$F$1)-1),"") -> 80 | E18: 8838.2 | H18: 15 | J18: =IF(H18<>"",RIGHT(DIARIO!$F$1,LEN(DIARIO!$F$1)-1),"") -> 80 | K18: 5900 | L18: 5900
D19: =IF(B19<>"",RIGHT(DIARIO!F4,LEN(DIARIO!F4)-1),"") | H19: 19 | J19: =IF(H19<>"",RIGHT(DIARIO!$F$1,LEN(DIARIO!$F$1)-1),"") -> 80 | K19: 749 | L19: 749
D20: =IF(B20<>"",RIGHT(DIARIO!F5,LEN(DIARIO!F5)-1),"") | H20: 23 | J20: =IF(H20<>"",RIGHT(DIARIO!$F$1,LEN(DIARIO!$F$1)-1),"") -> 80 | K20: 1500 | L20: 1500
D21: =IF(B21<>"",RIGHT(DIARIO!F6,LEN(DIARIO!F6)-1),"") | H21: 28 | J21: =IF(H21<>"",RIGHT(DIARIO!$F$1,LEN(DIARIO!$F$1)-1),"") -> 80 | K21: 580 | L21: 580
D22: =IF(B22<>"",RIGHT(DIARIO!F7,LEN(DIARIO!F7)-1),"") | J22: =IF(H22<>"",RIGHT(DIARIO!$F$1,LEN(DIARIO!$F$1)-1),"")
D23: =IF(B23<>"",RIGHT(DIARIO!F8,LEN(DIARIO!F8)-1),"") | J23: =IF(H23<>"",RIGHT(DIARIO!F15,LEN(DIARIO!F15)-1),"")
D24: =IF(B24<>"",RIGHT(DIARIO!F16,LEN(DIARIO!F16)-1),"") | J24: =IF(H24<>"",RIGHT(DIARIO!F16,LEN(DIARIO!F16)-1),"")
A26: =DIARIO!U5 -> Cuentas por Cobrar | I26: No. | K26: =DIARIO!V5 -> 112
A27: FECHA | C27: DETALLE | D27: REF. | E27: DÉBITO | G27: FECHA | I27: DETALLE | J27: REF. | K27: CRÉDITO
A28: Febrero | B28: 13 | D28: =IF(B28<>"",RIGHT(DIARIO!$F$1,LEN(DIARIO!$F$1)-1),"") -> 80 | E28: =(11800+11800*7%)*70% -> 8838.2 | G28: Febrero | H28: 13 | J28: =IF(H28<>"",RIGHT(DIARIO!$F$1,LEN(DIARIO!$F$1)-1),"") -> 80 | K28: =(11800+11800*7%)*70% -> 8838.2
D29: =IF(B29<>"",RIGHT(DIARIO!$F$1,LEN(DIARIO!$F$1)-1),"") | J29: =IF(H29<>"",RIGHT(DIARIO!$F$1,LEN(DIARIO!$F$1)-1),"")
D30: =IF(B30<>"",RIGHT(DIARIO!$F$1,LEN(DIARIO!$F$1)-1),"") | J30: =IF(H30<>"",RIGHT(DIARIO!$F$1,LEN(DIARIO!$F$1)-1),"")
D31: =IF(B31<>"",RIGHT(DIARIO!$F$1,LEN(DIARIO!$F$1)-1),"") | J31: =IF(H31<>"",RIGHT(DIARIO!$F$1,LEN(DIARIO!$F$1)-1),"")
D32: =IF(B32<>"",RIGHT(DIARIO!$F$1,LEN(DIARIO!$F$1)-1),"") | J32: =IF(H32<>"",RIGHT(DIARIO!$F$1,LEN(DIARIO!$F$1)-1),"")
D33: =IF(B33<>"",RIGHT(DIARIO!$F$1,LEN(DIARIO!$F$1)-1),"") | J33: =IF(H33<>"",RIGHT(DIARIO!$F$1,LEN(DIARIO!$F$1)-1),"")
D34: =IF(B34<>"",RIGHT(DIARIO!$F$1,LEN(DIARIO!$F$1)-1),"") | J34: =IF(H34<>"",RIGHT(DIARIO!$F$1,LEN(DIARIO!$F$1)-1),"")
D35: =IF(B35<>"",RIGHT(DIARIO!$F$1,LEN(DIARIO!$F$1)-1),"") | J35: =IF(H35<>"",RIGHT(DIARIO!$F$1,LEN(DIARIO!$F$1)-1),"")
D36: =IF(B36<>"",RIGHT(DIARIO!$F$1,LEN(DIARIO!$F$1)-1),"") | J36: =IF(H36<>"",RIGHT(DIARIO!$F$1,LEN(DIARIO!$F$1)-1),"")
A38: =DIARIO!U6 -> Mobiliario de Oficina | I38: No. | K38: =DIARIO!V6 -> 140
A39: FECHA | C39: DETALLE | D39: REF. | E39: DÉBITO | G39: FECHA | I39: DETALLE | J39: REF. | K39: CRÉDITO
A40: Febrero | B40: 3 | D40: =IF(B40<>"",RIGHT(DIARIO!$F$1,LEN(DIARIO!$F$1)-1),"") -> 80 | E40: 3400 | J40: =IF(H40<>"",RIGHT(DIARIO!$F$1,LEN(DIARIO!$F$1)-1),"")
D41: =IF(B41<>"",RIGHT(DIARIO!$F$1,LEN(DIARIO!$F$1)-1),"") | J41: =IF(H41<>"",RIGHT(DIARIO!$F$1,LEN(DIARIO!$F$1)-1),"")
D42: =IF(B42<>"",RIGHT(DIARIO!$F$1,LEN(DIARIO!$F$1)-1),"") | J42: =IF(H42<>"",RIGHT(DIARIO!$F$1,LEN(DIARIO!$F$1)-1),"")
D43: =IF(B43<>"",RIGHT(DIARIO!$F$1,LEN(DIARIO!$F$1)-1),"") | J43: =IF(H43<>"",RIGHT(DIARIO!$F$1,LEN(DIARIO!$F$1)-1),"")
D44: =IF(B44<>"",RIGHT(DIARIO!$F$1,LEN(DIARIO!$F$1)-1),"") | J44: =IF(H44<>"",RIGHT(DIARIO!$F$1,LEN(DIARIO!$F$1)-1),"")
D45: =IF(B45<>"",RIGHT(DIARIO!$F$1,LEN(DIARIO!$F$1)-1),"") | J45: =IF(H45<>"",RIGHT(DIARIO!$F$1,LEN(DIARIO!$F$1)-1),"")
D46: =IF(B46<>"",RIGHT(DIARIO!$F$1,LEN(DIARIO!$F$1)-1),"") | J46: =IF(H46<>"",RIGHT(DIARIO!$F$1,LEN(DIARIO!$F$1)-1),"")
D47: =IF(B47<>"",RIGHT(DIARIO!$F$1,LEN(DIARIO!$F$1)-1),"") | J47: =IF(H47<>"",RIGHT(DIARIO!$F$1,LEN(DIARIO!$F$1)-1),"")
D48: =IF(B48<>"",RIGHT(DIARIO!$F$1,LEN(DIARIO!$F$1)-1),"") | J48: =IF(H48<>"",RIGHT(DIARIO!$F$1,LEN(DIARIO!$F$1)-1),"")
A50: =DIARIO!U7 -> Equipo de Oficina | I50: No. | K50: =DIARIO!V7 -> 150
A51: FECHA | C51: DETALLE | D51: REF. | E51: DÉBITO | G51: FECHA | I51: DETALLE | J51: REF. | K51: CRÉDITO
A52: Febrero | B52: 5 | D52: =IF(B52<>"",RIGHT(DIARIO!$F$1,LEN(DIARIO!$F$1)-1),"") -> 80 | E52: 5600 | J52: =IF(H52<>"",RIGHT(DIARIO!$F$1,LEN(DIARIO!$F$1)-1),"")
D53: =IF(B53<>"",RIGHT(DIARIO!F13,LEN(DIARIO!F13)-1),"") | J53: =IF(H53<>"",RIGHT(DIARIO!$F$1,LEN(DIARIO!$F$1)-1),"")
D54: =IF(B54<>"",RIGHT(DIARIO!F14,LEN(DIARIO!F14)-1),"") | J54: =IF(H54<>"",RIGHT(DIARIO!$F$1,LEN(DIARIO!$F$1)-1),"")
D55: =IF(B55<>"",RIGHT(DIARIO!F15,LEN(DIARIO!F15)-1),"") | J55: =IF(H55<>"",RIGHT(DIARIO!$F$1,LEN(DIARIO!$F$1)-1),"")
D56: =IF(B56<>"",RIGHT(DIARIO!F16,LEN(DIARIO!F16)-1),"") | J56: =IF(H56<>"",RIGHT(DIARIO!$F$1,LEN(DIARIO!$F$1)-1),"")
D57: =IF(B57<>"",RIGHT(DIARIO!F17,LEN(DIARIO!F17)-1),"") | J57: =IF(H57<>"",RIGHT(DIARIO!$F$1,LEN(DIARIO!$F$1)-1),"")
D58: =IF(B58<>"",RIGHT(DIARIO!F18,LEN(DIARIO!F18)-1),"") | J58: =IF(H58<>"",RIGHT(DIARIO!$F$1,LEN(DIARIO!$F$1)-1),"")
D59: =IF(B59<>"",RIGHT(DIARIO!F19,LEN(DIARIO!F19)-1),"") | J59: =IF(H59<>"",RIGHT(DIARIO!$F$1,LEN(DIARIO!$F$1)-1),"")
A61: =DIARIO!U8 -> Cuentas por pagar | I61: No. | K61: =DIARIO!V8 -> 200
A62: FECHA | C62: DETALLE | D62: REF. | E62: DÉBITO | G62: FECHA | I62: DETALLE | J62: REF. | K62: CRÉDITO
A63: Febrero | B63: 23 | D63: =IF(B63<>"",RIGHT(DIARIO!$F$1,LEN(DIARIO!$F$1)-1),"") -> 80 | E63: 1500 | G63: Febrero | H63: 9 | J63: =IF(H63<>"",RIGHT(DIARIO!$F$1,LEN(DIARIO!$F$1)-1),"") -> 80 | K63: 2638
D64: =IF(B64<>"",RIGHT(DIARIO!$F$1,LEN(DIARIO!$F$1)-1),"") | J64: =IF(H64<>"",RIGHT(DIARIO!$F$1,LEN(DIARIO!$F$1)-1),"")
D65: =IF(B65<>"",RIGHT(DIARIO!$F$1,LEN(DIARIO!$F$1)-1),"") | J65: =IF(H65<>"",RIGHT(DIARIO!$F$1,LEN(DIARIO!$F$1)-1),"")
D66: =IF(B66<>"",RIGHT(DIARIO!$F$1,LEN(DIARIO!$F$1)-1),"") | J66: =IF(H66<>"",RIGHT(DIARIO!$F$1,LEN(DIARIO!$F$1)-1),"")
D67: =IF(B67<>"",RIGHT(DIARIO!$F$1,LEN(DIARIO!$F$1)-1),"") | J67: =IF(H67<>"",RIGHT(DIARIO!$F$1,LEN(DIARIO!$F$1)-1),"")
D68: =IF(B68<>"",RIGHT(DIARIO!$F$1,LEN(DIARIO!$F$1)-1),"") | J68: =IF(H68<>"",RIGHT(DIARIO!$F$1,LEN(DIARIO!$F$1)-1),"")
D69: =IF(B69<>"",RIGHT(DIARIO!$F$1,LEN(DIARIO!$F$1)-1),"") | J69: =IF(H69<>"",RIGHT(DIARIO!$F$1,LEN(DIARIO!$F$1)-1),"")
D70: =IF(B70<>"",RIGHT(DIARIO!$F$1,LEN(DIARIO!$F$1)-1),"") | J70: =IF(H70<>"",RIGHT(DIARIO!$F$1,LEN(DIARIO!$F$1)-1),"")
A72: =DIARIO!U9 -> Tesoro Nacional - ITBMS | I72: No. | K72: =DIARIO!V9 -> 201
A73: FECHA | C73: DETALLE | D73: REF. | E73: DÉBITO | G73: FECHA | I73: DETALLE | J73: REF. | K73: CRÉDITO
D74: =IF(B74<>"",RIGHT(DIARIO!$F$1,LEN(DIARIO!$F$1)-1),"") | G74: Febrero | H74: 13 | J74: =IF(H74<>"",RIGHT(DIARIO!$F$1,LEN(DIARIO!$F$1)-1),"") -> 80 | K74: 2638
D75: =IF(B75<>"",RIGHT(DIARIO!$F$1,LEN(DIARIO!$F$1)-1),"") | J75: =IF(H75<>"",RIGHT(DIARIO!$F$1,LEN(DIARIO!$F$1)-1),"")
D76: =IF(B76<>"",RIGHT(DIARIO!$F$1,LEN(DIARIO!$F$1)-1),"") | J76: =IF(H76<>"",RIGHT(DIARIO!$F$1,LEN(DIARIO!$F$1)-1),"")
D77: =IF(B77<>"",RIGHT(DIARIO!$F$1,LEN(DIARIO!$F$1)-1),"") | J77: =IF(H77<>"",RIGHT(DIARIO!$F$1,LEN(DIARIO!$F$1)-1),"")
D78: =IF(B78<>"",RIGHT(DIARIO!$F$1,LEN(DIARIO!$F$1)-1),"") | J78: =IF(H78<>"",RIGHT(DIARIO!$F$1,LEN(DIARIO!$F$1)-1),"")
D79: =IF(B79<>"",RIGHT(DIARIO!$F$1,LEN(DIARIO!$F$1)-1),"") | J79: =IF(H79<>"",RIGHT(DIARIO!$F$1,LEN(DIARIO!$F$1)-1),"")
D80: =IF(B80<>"",RIGHT(DIARIO!$F$1,LEN(DIARIO!$F$1)-1),"") | J80: =IF(H80<>"",RIGHT(DIARIO!$F$1,LEN(DIARIO!$F$1)-1),"")
D81: =IF(B81<>"",RIGHT(DIARIO!$F$1,LEN(DIARIO!$F$1)-1),"") | J81: =IF(H81<>"",RIGHT(DIARIO!$F$1,LEN(DIARIO!$F$1)-1),"")
A83: =DIARIO!U10 -> Capital | I83: No. | K83: =DIARIO!V10 -> 300
A84: FECHA | C84: DETALLE | D84: REF. | E84: DÉBITO | G84: FECHA | I84: DETALLE | J84: REF. | K84: CRÉDITO
D85: =IF(B85<>"",RIGHT(DIARIO!$F$1,LEN(DIARIO!$F$1)-1),"") | G85: Febrero | H85: 1 | J85: =IF(H85<>"",RIGHT(DIARIO!$F$1,LEN(DIARIO!$F$1)-1),"") -> 80 | K85: 185000
D86: =IF(B86<>"",RIGHT(DIARIO!$F$1,LEN(DIARIO!$F$1)-1),"") | J86: =IF(H86<>"",RIGHT(DIARIO!$F$1,LEN(DIARIO!$F$1)-1),"")
D87: =IF(B87<>"",RIGHT(DIARIO!$F$1,LEN(DIARIO!$F$1)-1),"") | J87: =IF(H87<>"",RIGHT(DIARIO!$F$1,LEN(DIARIO!$F$1)-1),"")
D88: =IF(B88<>"",RIGHT(DIARIO!$F$1,LEN(DIARIO!$F$1)-1),"") | J88: =IF(H88<>"",RIGHT(DIARIO!$F$1,LEN(DIARIO!$F$1)-1),"")
D89: =IF(B89<>"",RIGHT(DIARIO!$F$1,LEN(DIARIO!$F$1)-1),"") | J89: =IF(H89<>"",RIGHT(DIARIO!$F$1,LEN(DIARIO!$F$1)-1),"")
D90: =IF(B90<>"",RIGHT(DIARIO!$F$1,LEN(DIARIO!$F$1)-1),"") | J90: =IF(H90<>"",RIGHT(DIARIO!$F$1,LEN(DIARIO!$F$1)-1),"")
D91: =IF(B91<>"",RIGHT(DIARIO!$F$1,LEN(DIARIO!$F$1)-1),"") | J91: =IF(H91<>"",RIGHT(DIARIO!$F$1,LEN(DIARIO!$F$1)-1),"")
D92: =IF(B92<>"",RIGHT(DIARIO!$F$1,LEN(DIARIO!$F$1)-1),"") | J92: =IF(H92<>"",RIGHT(DIARIO!$F$1,LEN(DIARIO!$F$1)-1),"")
A94: =DIARIO!U11 -> Ingresos - Servicio Profesional | I94: No. | K94: =DIARIO!V11 -> 400
A95: FECHA | C95: DETALLE | D95: REF. | E95: DÉBITO | G95: FECHA | I95: DETALLE | J95: REF. | K95: CRÉDITO
D96: =IF(B96<>"",RIGHT(DIARIO!$F$1,LEN(DIARIO!$F$1)-1),"") | G96: Febrero | H96: 13 | J96: =IF(H96<>"",RIGHT(DIARIO!$F$1,LEN(DIARIO!$F$1)-1),"") -> 80 | K96: 11800
D97: =IF(B97<>"",RIGHT(DIARIO!$F$1,LEN(DIARIO!$F$1)-1),"") | J97: =IF(H97<>"",RIGHT(DIARIO!$F$1,LEN(DIARIO!$F$1)-1),"")
D98: =IF(B98<>"",RIGHT(DIARIO!$F$1,LEN(DIARIO!$F$1)-1),"") | J98: =IF(H98<>"",RIGHT(DIARIO!$F$1,LEN(DIARIO!$F$1)-1),"")
D99: =IF(B99<>"",RIGHT(DIARIO!$F$1,LEN(DIARIO!$F$1)-1),"") | J99: =IF(H99<>"",RIGHT(DIARIO!$F$1,LEN(DIARIO!$F$1)-1),"")
D100: =IF(B100<>"",RIGHT(DIARIO!$F$1,LEN(DIARIO!$F$1)-1),"") | J100: =IF(H100<>"",RIGHT(DIARIO!$F$1,LEN(DIARIO!$F$1)-1),"")
D101: =IF(B101<>"",RIGHT(DIARIO!$F$1,LEN(DIARIO!$F$1)-1),"") | J101: =IF(H101<>"",RIGHT(DIARIO!$F$1,LEN(DIARIO!$F$1)-1),"")
D102: =IF(B102<>"",RIGHT(DIARIO!$F$1,LEN(DIARIO!$F$1)-1),"") | J102: =IF(H102<>"",RIGHT(DIARIO!$F$1,LEN(DIARIO!$F$1)-1),"")
D103: =IF(B103<>"",RIGHT(DIARIO!$F$1,LEN(DIARIO!$F$1)-1),"") | J103: =IF(H103<>"",RIGHT(DIARIO!$F$1,LEN(DIARIO!$F$1)-1),"")
A105: =DIARIO!U12 -> Gasto - Salarios | I105: No. | K105: =DIARIO!V12 -> 600
A106: FECHA | C106: DETALLE | D106: REF. | E106: DÉBITO | G106: FECHA | I106: DETALLE | J106: REF. | K106: CRÉDITO
A107: Febrero | B107: 15 | D107: =IF(B107<>"",RIGHT(DIARIO!$F$1,LEN(DIARIO!$F$1)-1),"") -> 80 | E107: 11900 | F107: 794.39 | J107: =IF(H107<>"",RIGHT(DIARIO!$F$1,LEN(DIARIO!$F$1)-1),"")
D108: =IF(B108<>"",RIGHT(DIARIO!$F$1,LEN(DIARIO!$F$1)-1),"") | J108: =IF(H108<>"",RIGHT(DIARIO!$F$1,LEN(DIARIO!$F$1)-1),"")
D109: =IF(B109<>"",RIGHT(DIARIO!$F$1,LEN(DIARIO!$F$1)-1),"") | J109: =IF(H109<>"",RIGHT(DIARIO!$F$1,LEN(DIARIO!$F$1)-1),"")
D110: =IF(B110<>"",RIGHT(DIARIO!$F$1,LEN(DIARIO!$F$1)-1),"") | J110: =IF(H110<>"",RIGHT(DIARIO!$F$1,LEN(DIARIO!$F$1)-1),"")
...

Sheet DIARIO
A1: DIARIO | F1: *80 | I1: =UPPER(U3&"-"&V3) -> CAJA MENUDA-101 | M1: =UPPER(U4&"-"&V4) -> BANCO-110 | Q1: =UPPER(U5&"-"&V5) -> CUENTAS POR COBRAR-112 | AA1: Cuenta | AB1: Código
I2: DR | J2: CR | M2: DR | N2: CR | Q2: DR | R2: CR | AA2: Caja general | AB2: 100 | AC2: 100
H3: 3 | I3: 300 | L3: 1 | M3: 185000 | N3: 300 | O3: 3 | P3: 13 | Q3: =(11800+11800*7%)*70% -> 8838.2 | R3: =(11800+11800*7%)*70% -> 8838.2 | S3: 23 | U3: {=_xlfn._xlws.SORT(_xlfn.UNIQUE(_xlfn._xlws.FILTER(C7:D51,ISNUMBER(D7:D51))),2,1)} -> Caja Menuda | V3: 101 | AA3: Caja menuda | AB3: 101
L4: 13 | M4: =(11800+11800*7%)*30% -> 3787.8 | N4: =5600+5600*7% -> 5992 | O4: 5 | U4: Banco | V4: 110 | AA4: Banco | AB4: 110
A5: FECHA | C5: DETALLE | D5: REF | E5: DR | F5: CR | L5: 23 | M5: =(11800+11800*7%)*70% -> 8838.2 | N5: 5900 | O5: 15 | U5: Cuentas por Cobrar | V5: 112 | AA5: Cuentas por cobrar | AB5: 112
A6: 2026 | N6: 749 | O6: 19 | U6: Mobiliario de Oficina | V6: 140 | AA6: Terreno | AB6: 120
A7: Febrero | B7: 1 | C7: Banco | D7: =IFERROR(VLOOKUP(C7,$AA$2:$AB$40,2,FALSE),"") -> 110 | E7: 185000 | N7: 1500 | O7: 23 | U7: Equipo de Oficina | V7: 150 | AA7: Edificio | AB7: 130
C8: Capital | D8: =IFERROR(VLOOKUP(C8,$AA$2:$AB$40,2,FALSE),"") -> 300 | F8: 185000 | N8: 580 | O8: 28 | U8: Cuentas por pagar | V8: 200 | AA8: Edificio - caseta | AB8: 130
C9: Registro de aporte de capital al banco Scotiabank.NAMÁ, S.A | D9: =IFERROR(VLOOKUP(C9,$AA$2:$AB$40,2,FALSE),"") | U9: Tesoro Nacional - ITBMS | V9: 201 | AA9: Mobiliario de oficina | AB9: 140
B10: 3 | C10: Caja Menuda | D10: =IFERROR(VLOOKUP(C10,$AA$2:$AB$40,2,FALSE),"") -> 101 | E10: 300 | U10: Capital | V10: 300 | AA10: Mobiliario de oficina - señalizaciones | AB10: 140
C11: Banco | D11: =IFERROR(VLOOKUP(C11,$AA$2:$AB$40,2,FALSE),"") -> 110 | F11: 300 | U11: Ingresos - Servicio Profesional | V11: 400 | AA11: Equipo de oficina | AB11: 150
C12: Se establece caja menuda mediante el cheque No . 2201 | D12: =IFERROR(VLOOKUP(C12,$AA$2:$AB$40,2,FALSE),"") | I12: =SUM(I3:I11) -> 300 | J12: =SUM(J3:J11) -> 0 | M12: =SUM(M3:M11) -> 197626 | N12: =SUM(N3:N11) -> 15021 | Q12: =SUM(Q3:Q11) -> 8838.2 | R12: =SUM(R3:R11) -> 8838.2 | U12: Gasto - Salarios | V12: 600 | AA12: Cuentas por pagar | AB12: 200
B13: 5 | C13: Equipo de Oficina | D13: =IFERROR(VLOOKUP(C13,$AA$2:$AB$40,2,FALSE),"") -> 150 | E13: 5600 | I13: =IF(I12>J12,I12-J12,"") -> 300 | J13: =IF(J12>I12,J12-I12,"") | M13: =IF(M12>N12,M12-N12,"") -> 182605 | N13: =IF(N12>M12,N12-M12,"") | Q13: =IF(Q12>R12,Q12-R12,"") | R13: =IF(R12>Q12,R12-Q12,"") | U13: Gasto - Publicidad | V13: 602 | AA13: Tesoro nacional - ITBMS | AB13: 201
C14: Gasto - ITBMS | D14: =IFERROR(VLOOKUP(C14,$AA$2:$AB$40,2,FALSE),"") -> 606 | E14: =E13*7% -> 392 | U14: Gastos - servicios públicos | V14: 603 | AA14: Documentos por pagar | AB14: 210
C15: Banco | D15: =IFERROR(VLOOKUP(C15,$AA$2:$AB$40,2,FALSE),"") -> 110 | F15: =5600+5600*7% -> 5992 | I15: =UPPER(U6&"-"&V6) -> MOBILIARIO DE OFICINA-140 | M15: =UPPER(U7&"-"&V7) -> EQUIPO DE OFICINA-150 | Q15: =UPPER(U8&"-"&V8) -> CUENTAS POR PAGAR-200 | U15: Gasto - ITBMS | V15: 606 | AA15: Salarios por pagar | AB15: 220
C16: Compra de equipo de herramientas para instalación de redes mediante el cheque No. 2202 | D16: =IFERROR(VLOOKUP(C16,$AA$2:$AB$40,2,FALSE),"") | I16: DR | J16: CR | M16: DR | N16: CR | Q16: DR | R16: CR | AA16: Capital | AB16: 300
B17: 9 | C17: Mobiliario de Oficina | D17: =IFERROR(VLOOKUP(C17,$AA$2:$AB$40,2,FALSE),"") -> 140 | E17: 3400 | H17: 9 | I17: 3400 | L17: 5 | M17: 5600 | P17: 23 | Q17: 1500 | R17: 2638 | S17: 9 | AA17: Personal o retiros | AB17: 301
C18: Gasto - ITBMS | D18: =IFERROR(VLOOKUP(C18,$AA$2:$AB$40,2,FALSE),"") -> 606 | E18: =3400*7% -> 238 | AA18: Ingresos - servicio profesional | AB18: 400
C19: Cuentas por pagar | D19: =IFERROR(VLOOKUP(C19,$AA$2:$AB$40,2,FALSE),"") -> 200 | F19: =E18+E17 -> 3638 | AA19: Ingresos - servicios profesionales | AB19: 400
C20: Compra de mobiliario de oficina a credito | D20: =IFERROR(VLOOKUP(C20,$AA$2:$AB$40,2,FALSE),"") | AA20: Ingresos - honorarios profesionales | AB20: 400
B21: 13 | C21: Cuentas por Cobrar | D21: =IFERROR(VLOOKUP(C21,$AA$2:$AB$40,2,FALSE),"") -> 112 | E21: =(11800+11800*7%)*70% -> 8838.2 | AA21: Gasto - sueldo | AB21: 600
C22: Banco | D22: =IFERROR(VLOOKUP(C22,$AA$2:$AB$40,2,FALSE),"") -> 110 | E22: =(11800+11800*7%)*30% -> 3787.8 | AA22: Gastos - sueldo | AB22: 600
C23: Tesoro Nacional - ITBMS | D23: =IFERROR(VLOOKUP(C23,$AA$2:$AB$40,2,FALSE),"") -> 201 | F23: =11800*7% -> 826 | AA23: Gastos - sueldos | AB23: 600
C24: Ingresos - Servicio Profesional | D24: =IFERROR(VLOOKUP(C24,$AA$2:$AB$40,2,FALSE),"") -> 400 | F24: 11800 | AA24: Gasto - salarios | AB24: 600
C25: Se presta un servicio de implementación de red corporativa | D25: =IFERROR(VLOOKUP(C25,$AA$2:$AB$40,2,FALSE),"") | AA25: Gasto - transporte | AB25: 601
B26: 15 | C26: Gasto - Salarios | D26: =IFERROR(VLOOKUP(C26,$AA$2:$AB$40,2,FALSE),"") -> 600 | E26: 5900 | I26: =SUM(I17:I25) -> 3400 | J26: =SUM(J17:J25) -> 0 | M26: =SUM(M17:M25) -> 5600 | N26: =SUM(N17:N25) -> 0 | Q26: =SUM(Q17:Q25) -> 1500 | R26: =SUM(R17:R25) -> 2638 | AA26: Gastos - alquiler | AB26: 601
C27: Banco | D27: =IFERROR(VLOOKUP(C27,$AA$2:$AB$40,2,FALSE),"") -> 110 | F27: 5900 | I27: =IF(I26>J26,I26-J26,"") -> 3400 | J27: =IF(J26>I26,J26-I26,"") | M27: =IF(M26>N26,M26-N26,"") -> 5600 | N27: =IF(N26>M26,N26-M26,"") | Q27: =IF(Q26>R26,Q26-R26,"") | R27: =R26-Q26 -> 1138 | AA27: Gastos - jardinero | AB27: 601
C28: Pago de salarios mediante el cheque No. 2203 | D28: =IFERROR(VLOOKUP(C28,$AA$2:$AB$40,2,FALSE),"") | AA28: Gasto - licencias de software | AB28: 601
B29: 19 | C29: Gasto - Publicidad | D29: =IFERROR(VLOOKUP(C29,$AA$2:$AB$40,2,FALSE),"") -> 602 | E29: =749 - 749*7% -> 696.57 | I29: =UPPER(U9&"-"&V9) -> TESORO NACIONAL - ITBMS-201 | M29: =UPPER(U10&"-"&V10) -> CAPITAL-300 | Q29: =UPPER(U11&"-"&V11) -> INGRESOS - SERVICIO PROFESIONAL-400 | AA29: Gasto - publicidad | AB29: 602
C30: Gasto - ITBMS | D30: =IFERROR(VLOOKUP(C30,$AA$2:$AB$40,2,FALSE),"") -> 606 | E30: =749*7% -> 52.43 | I30: DR | J30: CR | M30: DR | N30: CR | Q30: DR | R30: CR | AA30: Gastos - electricidad | AB30: 602
C31: Banco | D31: =IFERROR(VLOOKUP(C31,$AA$2:$AB$40,2,FALSE),"") -> 110 | F31: =E30+E29 -> 749 | J31: =11800*7% -> 826 | K31: 13 | N31: 185000 | O31: 1 | R31: 11800 | S31: 13 | AA31: Gasto - teléfono | AB31: 602
C32: Pago de gastos de mercadeo mediante el cheque No. 2204 | D32: =IFERROR(VLOOKUP(C32,$AA$2:$AB$40,2,FALSE),"") | AA32: Gastos - teléfono | AB32: 603
B33: 23 | C33: Banco | D33: =IFERROR(VLOOKUP(C33,$AA$2:$AB$40,2,FALSE),"") -> 110 | E33: =(11800+11800*7%)*70% -> 8838.2 | AA33: Gastos - servicios públicos | AB33: 603
C34: Cuentas por Cobrar | D34: =IFERROR(VLOOKUP(C34,$AA$2:$AB$40,2,FALSE),"") -> 112 | F34: =(11800+11800*7%)*70% -> 8838.2 | AA34: Gasto - electricidad | AB34: 603
C35: Se recibe transferencia bancaria por el saldo pendiente de la venta del 13 de febrero. | D35: =IFERROR(VLOOKUP(C35,$AA$2:$AB$40,2,FALSE),"") | AA35: Gasto - internet | AB35: 604
B36: 26 | C36: Cuentas por Pagar | D36: =IFERROR(VLOOKUP(C36,$AA$2:$AB$40,2,FALSE),"") -> 200 | E36: 1500 | AA36: Gastos - agua | AB36: 604
C37: Banco | D37: =IFERROR(VLOOKUP(C37,$AA$2:$AB$40,2,FALSE),"") -> 110 | F37: 1500 | AA37: Gasto - agua | AB37: 605
C38: Se realiza abono al mobiliario mediante el cheque No. 2205 | D38: =IFERROR(VLOOKUP(C38,$AA$2:$AB$40,2,FALSE),"") | AA38: Gasto - ITBMS | AB38: 606
B39: 28 | C39: Gastos - servicios públicos | D39: =IFERROR(VLOOKUP(C39,$AA$2:$AB$40,2,FALSE),"") -> 603 | E39: =580*93% -> 539.4 | AA39: Gasto - honorario profesional | AB39: 607
C40: Gasto - ITBMS | D40: =IFERROR(VLOOKUP(C40,$AA$2:$AB$40,2,FALSE),"") -> 606 | E40: =580*7% -> 40.6 | AA40: Legales y notariales | AB40: 608
C41: Banco | D41: =IFERROR(VLOOKUP(C41,$AA$2:$AB$40,2,FALSE),"") -> 110 | F41: =E39+E40 -> 580 | I41: =SUM(I31:I40) -> 0 | J41: =SUM(J31:J40) -> 826 | M41: =SUM(M31:M40) -> 0 | N41: =SUM(N31:N40) -> 185000 | Q41: =SUM(Q31:Q40) -> 0 | R41: =SUM(R31:R40) -> 11800
C42: Pago de servicio publico mediante el cheque No. 2205 | D42: =IFERROR(VLOOKUP(C42,$AA$2:$AB$40,2,FALSE),"") | I42: =IF(I41>J41,I41-J41,"") | J42: =IF(J41>I41,J41-I41,"") -> 826 | M42: =IF(M41>N41,M41-N41,"") | N42: =IF(N41>M41,N41-M41,"") -> 185000 | Q42: =IF(Q41>R41,Q41-R41,"") | R42: =IF(R41>Q41,R41-Q41,"") -> 11800
D43: =IFERROR(VLOOKUP(C43,$AA$2:$AB$40,2,FALSE),"")
D44: =IFERROR(VLOOKUP(C44,$AA$2:$AB$40,2,FALSE),"") | I44: =UPPER(U12&"-"&V12) -> GASTO - SALARIOS-600 | M44: =UPPER(U13&"-"&V13) -> GASTO - PUBLICIDAD-602 | Q44: =UPPER(U14&"-"&V14) -> GASTOS - SERVICIOS PÚBLICOS-603
D45: =IFERROR(VLOOKUP(C45,$AA$2:$AB$40,2,FALSE),"") | I45: DR | J45: CR | M45: DR | N45: CR | Q45: DR | R45: CR
D46: =IFERROR(VLOOKUP(C46,$AA$2:$AB$40,2,FALSE),"") | H46: 15 | I46: 5900 | L46: 19 | M46: =749 - 749*7% -> 696.57 | P46: 28 | Q46: =580*93% -> 539.4
D47: =IFERROR(VLOOKUP(C47,$AA$2:$AB$40,2,FALSE),"")
D48: =IFERROR(VLOOKUP(C48,$AA$2:$AB$40,2,FALSE),"")
D49: =IFERROR(VLOOKUP(C49,$AA$2:$AB$40,2,FALSE),"")
D50: =IFERROR(VLOOKUP(C50,$AA$2:$AB$40,2,FALSE),"")
D51: =IFERROR(VLOOKUP(C51,$AA$2:$AB$40,2,FALSE),"")
I55: =SUM(I46:I54) -> 5900 | J55: =SUM(J46:J54) -> 0 | M55: =SUM(M46:M54) -> 696.57 | N55: =SUM(N46:N54) -> 0 | Q55: =SUM(Q46:Q54) -> 539.4 | R55: =SUM(R46:R54) -> 0
I56: =IF(I55>J55,I55-J55,"") -> 5900 | J56: =IF(J55>I55,J55-I55,"") | M56: =IF(M55>N55,M55-N55,"") -> 696.57 | N56: =IF(N55>M55,N55-M55,"") | Q56: =IF(Q55>R55,Q55-R55,"") -> 539.4 | R56: =IF(R55>Q55,R55-Q55,"")
I58: =UPPER(U15&"-"&V15) -> GASTO - ITBMS-606 | M58: =UPPER(U16&"-"&V16) -> - | Q58: =UPPER(U17&"-"&V17) -> -
I59: DR | J59: CR | M59: DR | N59: CR | Q59: DR | R59: CR
H60: 5 | I60: 392
H61: 9 | I61: =3400*7% -> 238
H62: 19 | I62: =749*7% -> 52.43
H63: 28 | I63: =580*7% -> 40.6
I69: =SUM(I60:I68) -> 723.03 | J69: =SUM(J60:J68) -> 0 | M69: =SUM(M60:M68) -> 0 | N69: =SUM(N60:N68) -> 0 | Q69: =SUM(Q60:Q68) -> 0 | R69: =SUM(R60:R68) -> 0
I70: =IF(I69>J69,I69-J69,"") -> 723.03 | J70: =IF(J69>I69,J69-I69,"") | M70: =IF(M69>N69,M69-N69,"") | N70: =IF(N69>M69,N69-M69,"") | Q70: =IF(Q69>R69,Q69-R69,"") | R70: =IF(R69>Q69,R69-Q69,"")
